rhyton/__init__.py
rhyton/dev.py
rhyton/test.py
rhyton/transpile_test/for_statement.r
rhyton/transpile_test/func.r
rhyton/transpile_test/if_statement.r
rhyton/transpile_test/var_definition.r
rhyton/transpiler.py
rhyton-0.0.4.dist-info/METADATA
rhyton-0.0.4.dist-info/WHEEL
rhyton-0.0.4.dist-info/RECORD
