Metadata-Version: 2.1
Name: rhyton
Version: 0.0.4
Summary: R to Python transpiler
Author: Dmitriy Din
Author-email: dmitriy1d01@gmail.com
Requires-Python: >=3.9,<4.0
Classifier: Programming Language :: Python :: 3
Classifier: Programming Language :: Python :: 3.9
Classifier: Programming Language :: Python :: 3.10
Classifier: Programming Language :: Python :: 3.11
Requires-Dist: astor (>=0.8.1,<0.9.0)
Requires-Dist: pydocstyle (>=6.3.0,<7.0.0)
Requires-Dist: rich (>=13.3.5,<14.0.0)
Requires-Dist: sexpdata (>=1.0.0,<2.0.0)
Requires-Dist: tree-sitter (>=0.20.1,<0.21.0)
Requires-Dist: tree-sitter-languages (>=1.5.0,<2.0.0)
